damona/__init__.py
damona/admin.py
damona/biocontainers/__init__.py
damona/biocontainers/registry.yaml
damona/builders.py
damona/common.py
damona/config.py
damona/environ.py
damona/install.py
damona/library/R/Makefile
damona/library/R/Singularity.R_3.6.3
damona/library/R/Singularity.R_4.0.2
damona/library/R/registry.yaml
damona/library/__init__.py
damona/library/conda/README.rst
damona/library/conda/Singularity.conda_4.7.12
damona/library/conda/Singularity.conda_4.9.2
damona/library/conda/registry.yaml
damona/library/micromamba/Singularity.micromamba_1.4.3
damona/library/micromamba/Singularity.micromamba_1.5.8
damona/library/micromamba/registry.yaml
damona/papers/__init__.py
damona/registry.py
damona/script.py
damona/shell/__init__.py
damona/shell/bash/__init__.py
damona/shell/bash/damona.sh
damona/shell/fish/damona.fish
damona/shell/zsh/__init__.py
damona/shell/zsh/damona.zsh
damona/software/__init__.py
damona/software/adapterremoval/Singularity.adapterremoval_2.3.3
damona/software/adapterremoval/registry.yaml
damona/software/art/README
damona/software/art/Singularity.art_2.3.7
damona/software/art/Singularity.art_2.5.8
damona/software/art/Singularity.art_3.11.14
damona/software/art/registry.yaml
damona/software/augustus/Singularity.augustus_3.5.0
damona/software/augustus/registry.yaml
damona/software/bamtools/README.rst
damona/software/bamtools/Singularity.bamtools_2.5.2
damona/software/bamtools/registry.yaml
damona/software/bandage/Singularity.bandage_0.8.1
damona/software/bandage/registry.yaml
damona/software/bbmap/Singularity.bbmap_39.1.0
damona/software/bbmap/registry.yaml
damona/software/bbtools/Singularity.bbtools_38.94.0
damona/software/bbtools/registry.yaml
damona/software/bcftools/Singularity.bctools_1.16.0
damona/software/bcftools/registry.yaml
damona/software/bcl-convert/README
damona/software/bcl-convert/Singularity.bcl-convert_4.2.7
damona/software/bcl-convert/registry.yaml
damona/software/bcl2fastq/README.rst
damona-0.16.dist-info/LICENSE
damona-0.16.dist-info/METADATA
damona-0.16.dist-info/WHEEL
damona-0.16.dist-info/entry_points.txt
damona-0.16.dist-info/RECORD
