Metadata-Version: 2.3
Name: damona
Version: 0.16
Summary: A manager of singularity containers and their singularity recipes (NGS applications)
License: BSD-3
Keywords: snakemake, sequana, RNAseq, RNADiff, differential analysis
Author: Thomas Cokelaer
Author-email: thomas.cokelaer@pasteur.fr
Requires-Python: >=3.8,<4.0
Classifier: Development Status :: 5 - Production/Stable
Classifier: Intended Audience :: Education
Classifier: Intended Audience :: End Users/Desktop
Classifier: Intended Audience :: Developers
Classifier: Intended Audience :: Science/Research
Classifier: License :: OSI Approved :: BSD License
Classifier: Operating System :: POSIX :: Linux
Classifier: Programming Language :: Python :: 3.8
Classifier: Programming Language :: Python :: 3.9
Classifier: Programming Language :: Python :: 3.10
Classifier: Topic :: Software Development :: Libraries :: Python Modules
Classifier: Topic :: Scientific/Engineering :: Bio-Informatics
Classifier: Topic :: Scientific/Engineering :: Information Analysis
Requires-Dist: beautifulsoup4 (>=4.12.3,<5.0.0)
Requires-Dist: click (>=8.1.8,<9.0.0)
Requires-Dist: click-completion (>=0.5.2,<0.6.0)
Requires-Dist: colorlog (>=6.9.0,<7.0.0)
Requires-Dist: easydev (>=0.13.3,<0.14.0)
Requires-Dist: loguru (>=0.7.3,<0.8.0)
Requires-Dist: packaging (>=24.2,<25.0)
Requires-Dist: pyyaml (>=6.0.2,<7.0.0)
Requires-Dist: requests (>=2.32.3,<3.0.0)
Requires-Dist: rich-click (>=1.8.5,<2.0.0)
Requires-Dist: spython (>=0.3.14,<0.4.0)
Requires-Dist: tqdm (>=4.67.1,<5.0.0)
